fx_shared_models-0.2.83.dist-info/licenses/LICENSE
shared_models/__init__.py
shared_models/constants.py
shared_models/accounts/__init__.py
shared_models/accounts/apps.py
shared_models/accounts/models.py
shared_models/accounts/migrations/0001_initial.py
shared_models/accounts/migrations/0002_remove_account_group_type_account_has_bonus_and_more.py
shared_models/accounts/migrations/0003_account_is_archived_account_is_trading_enabled.py
shared_models/accounts/migrations/0004_alter_account_created_at_alter_account_created_by_and_more.py
shared_models/accounts/migrations/0005_account_currency.py
shared_models/accounts/migrations/0006_alter_account_options.py
shared_models/accounts/migrations/0007_alter_account_options.py
shared_models/accounts/migrations/__init__.py
shared_models/common/base.py
shared_models/common/mixins.py
shared_models/common/utils.py
shared_models/company_ba/__init__.py
shared_models/company_ba/apps.py
shared_models/company_ba/models.py
shared_models/company_ba/migrations/0001_initial.py
shared_models/company_ba/migrations/0002_alter_companybankaccount_options.py
shared_models/company_ba/migrations/__init__.py
shared_models/crypto_wallet/__init__.py
shared_models/crypto_wallet/apps.py
shared_models/crypto_wallet/models.py
shared_models/crypto_wallet/migrations/0001_initial.py
shared_models/crypto_wallet/migrations/0002_alter_companycryptowallet_options.py
shared_models/crypto_wallet/migrations/__init__.py
shared_models/customer_crypto_wallet/__init__.py
shared_models/customer_crypto_wallet/apps.py
shared_models/customer_crypto_wallet/models.py
shared_models/customer_crypto_wallet/migrations/0001_initial.py
shared_models/customer_crypto_wallet/migrations/0002_alter_customercryptowallet_options.py
shared_models/customer_crypto_wallet/migrations/__init__.py
shared_models/customer_upi/__init__.py
shared_models/customer_upi/apps.py
shared_models/customer_upi/models.py
shared_models/customer_upi/migrations/0001_initial.py
shared_models/customer_upi/migrations/0002_alter_customerupi_options.py
fx_shared_models-0.2.83.dist-info/METADATA
fx_shared_models-0.2.83.dist-info/WHEEL
fx_shared_models-0.2.83.dist-info/top_level.txt
fx_shared_models-0.2.83.dist-info/RECORD
