Metadata-Version: 2.4
Name: fx-shared-models
Version: 0.2.83
Summary: Shared models for FX Backend
Home-page: https://github.com/fxbackend/fx-shared-models
Author: FX Backend
Author-email: fxbackend@gmail.com
Classifier: Development Status :: 3 - Alpha
Classifier: Intended Audience :: Developers
Classifier: License :: OSI Approved :: MIT License
Classifier: Programming Language :: Python :: 3
Classifier: Programming Language :: Python :: 3.8
Classifier: Framework :: Django
Requires-Python: >=3.8
License-File: LICENSE
Requires-Dist: Django>=4.2
Requires-Dist: django-environ>=0.10.0
Requires-Dist: djangorestframework>=3.14.0
Requires-Dist: pytz
Requires-Dist: django-encrypted-model-fields>=0.6.0
Dynamic: author
Dynamic: author-email
Dynamic: classifier
Dynamic: description
Dynamic: description-content-type
Dynamic: home-page
Dynamic: license-file
Dynamic: requires-dist
Dynamic: requires-python
Dynamic: summary
